{
  "mcpServers": {
    "5118-seo-adapter": {
      "type": "stdio",
      "command": "node",
      "args": [
        "/Users/axe/work/seo/5118-seo-adapter/dist/index.js"
      ],
      "env": {
        "API_5118_LONGTAIL_V2": "your-5118-longtail-key",
        "API_5118_FREQ_WORDS": "your-5118-frequency-key",
        "API_5118_SUGGEST": "your-5118-suggest-key",
        "API_5118_KW_PARAM_V2": "your-5118-keyword-metrics-key",
        "API_5118_TRAFFIC": "your-5118-traffic-key"
      }
    }
  }
}
